MANIFEST.in
README.rst
setup.py
alpine/__init__.py
alpine/alpineobject.py
alpine/apiclient.py
alpine/datasource.py
alpine/exception.py
alpine/job.py
alpine/logging.json
alpine/user.py
alpine/workfile.py
alpine/workspace.py
alpine.egg-info/PKG-INFO
alpine.egg-info/SOURCES.txt
alpine.egg-info/dependency_links.txt
alpine.egg-info/not-zip-safe
alpine.egg-info/requires.txt
alpine.egg-info/top_level.txt