Metadata-Version: 1.1
Name: alpine
Version: 1.0.12
Summary: Alpine Web API Client
Home-page: https://github.com/AlpineNow/python-alpine-api
Author: Alpine Data, Inc.
Author-email: ggao@alpinenow.com
License: MIT License
Keywords: alpine api sdk chorus
Platform: Linux; MacOS X; Windows
Classifier: Development Status :: 2 - Pre-Alpha
Classifier: Intended Audience :: Developers
Classifier: Operating System :: OS Independent
Classifier: Topic :: Internet
Classifier: Programming Language :: Python :: 2.7
Classifier: Programming Language :: Python :: 3.2
Classifier: Programming Language :: Python :: 3.3
Classifier: Programming Language :: Python :: 3.4
Classifier: Programming Language :: Python :: 3.5
Classifier: Programming Language :: Python :: 3.6
